bambara_normalizer/__init__.py
bambara_normalizer/cli.py
bambara_normalizer/config.py
bambara_normalizer/dates.py
bambara_normalizer/evaluation.py
bambara_normalizer/measurements.py
bambara_normalizer/normalizer.py
bambara_normalizer/numbers.py
bambara_normalizer/py.typed
bambara_normalizer/times.py
bambara_normalizer/utils.py
bambara_text_normalizer-1.0.1.dist-info/licenses/LICENSE
bambara_text_normalizer-1.0.1.dist-info/METADATA
bambara_text_normalizer-1.0.1.dist-info/WHEEL
bambara_text_normalizer-1.0.1.dist-info/entry_points.txt
bambara_text_normalizer-1.0.1.dist-info/top_level.txt
bambara_text_normalizer-1.0.1.dist-info/RECORD
