Metadata-Version: 2.4
Name: bambara-text-normalizer
Version: 1.0.1
Summary: Text normalization (TN/ITN) and ASR evaluation framework for Bambara (Bamanankan) language processing
Author-email: sudoping01 <sudoping01@gmail.com>
Maintainer-email: sudoping01 <sudoping01@gmail.com>
License: MIT
Project-URL: Homepage, https://github.com/MALIBA-AI/bambara-normalizer
Project-URL: Documentation, https://github.com/MALIBA-AI/bambara-normalizer
Project-URL: Repository, https://github.com/MALIBA-AI/bambara-normalizer
Project-URL: Issues, https://github.com/MALIBA-AI/bambara-normalizer/issues
Keywords: bambara,bamanankan,asr,speech-recognition,text-normalization,wer,nlp,african-languages,manding,mali
Classifier: Development Status :: 5 - Production/Stable
Classifier: Intended Audience :: Developers
Classifier: Intended Audience :: Science/Research
Classifier: License :: OSI Approved :: MIT License
Classifier: Operating System :: OS Independent
Classifier: Programming Language :: Python :: 3
Classifier: Programming Language :: Python :: 3.8
Classifier: Programming Language :: Python :: 3.9
Classifier: Programming Language :: Python :: 3.10
Classifier: Programming Language :: Python :: 3.11
Classifier: Programming Language :: Python :: 3.12
Classifier: Topic :: Scientific/Engineering :: Artificial Intelligence
Classifier: Topic :: Text Processing :: Linguistic
Requires-Python: >=3.8
License-File: LICENSE
Requires-Dist: jiwer>=3.0.0
Provides-Extra: dev
Requires-Dist: pytest>=7.0; extra == "dev"
Requires-Dist: pytest-cov>=4.0; extra == "dev"
Requires-Dist: black>=23.0; extra == "dev"
Requires-Dist: isort>=5.0; extra == "dev"
Requires-Dist: mypy>=1.0; extra == "dev"
Requires-Dist: ruff>=0.1.0; extra == "dev"
Provides-Extra: docs
Requires-Dist: sphinx>=6.0; extra == "docs"
Requires-Dist: sphinx-rtd-theme>=1.0; extra == "docs"
Dynamic: license-file
